CHANGES (links).txt
CHANGES.txt
CONTRIBUTORS.txt
DEVGUIDE.txt
MANIFEST.in
README.txt
distribute_setup.py
easy_install.py
launcher.c
pkg_resources.py
release.py
setup.cfg
setup.py
site.py
_markerlib/__init__.py
_markerlib/markers.py
distribute.egg-info/PKG-INFO
distribute.egg-info/SOURCES.txt
distribute.egg-info/dependency_links.txt
distribute.egg-info/entry_points.txt
distribute.egg-info/top_level.txt
distribute.egg-info/zip-safe
docs/Makefile
docs/conf.py
docs/easy_install.txt
docs/index.txt
docs/pkg_resources.txt
docs/python3.txt
docs/roadmap.txt
docs/setuptools.txt
docs/using.txt
docs/_templates/indexsidebar.html
docs/_theme/nature/theme.conf
docs/_theme/nature/static/nature.css_t
docs/_theme/nature/static/pygments.css
docs/build/html/_sources/easy_install.txt
docs/build/html/_sources/index.txt
docs/build/html/_sources/pkg_resources.txt
docs/build/html/_sources/python3.txt
docs/build/html/_sources/roadmap.txt
docs/build/html/_sources/setuptools.txt
docs/build/html/_sources/using.txt
docs/build/html/_static/basic.css
docs/build/html/_static/nature.css
docs/build/html/_static/pygments.css
setuptools/__init__.py
setuptools/archive_util.py
setuptools/cli-32.exe
setuptools/cli-64.exe
setuptools/cli-arm-32.exe
setuptools/depends.py
setuptools/dist.py
setuptools/extension.py
setuptools/gui-32.exe
setuptools/gui-64.exe
setuptools/gui-arm-32.exe
setuptools/package_index.py
setuptools/sandbox.py
setuptools/script template (dev).py
setuptools/script template.py
setuptools/command/__init__.py
setuptools/command/alias.py
setuptools/command/bdist_egg.py
setuptools/command/bdist_rpm.py
setuptools/command/bdist_wininst.py
setuptools/command/build_ext.py
setuptools/command/build_py.py
setuptools/command/develop.py
setuptools/command/easy_install.py
setuptools/command/egg_info.py
setuptools/command/install.py
setuptools/command/install_egg_info.py
setuptools/command/install_lib.py
setuptools/command/install_scripts.py
setuptools/command/launcher manifest.xml
setuptools/command/register.py
setuptools/command/rotate.py
setuptools/command/saveopts.py
setuptools/command/sdist.py
setuptools/command/setopt.py
setuptools/command/test.py
setuptools/command/upload.py
